{
  "title": "Identity and culture (part 11)",
  "cards": [
    {
      "side1": "restare",
      "side2": "to stay, remain"
    },
    {
      "side1": "ricevere",
      "side2": "to receive"
    },
    {
      "side1": "ridere",
      "side2": "to laugh"
    },
    {
      "side1": "riso, il",
      "side2": "rice"
    },
    {
      "side1": "ritornare",
      "side2": "to return"
    },
    {
      "side1": "rivista, la",
      "side2": "magazine"
    },
    {
      "side1": "scacchi, gli",
      "side2": "chess"
    },
    {
      "side1": "scoprire",
      "side2": "to discover"
    },
    {
      "side1": "sottotitoli, i",
      "side2": "subtitles"
    },
    {
      "side1": "speciale",
      "side2": "special"
    },
    {
      "side1": "spedire un pacco",
      "side2": "to send a parcel"
    },
    {
      "side1": "spendere",
      "side2": "to spend - money"
    },
    {
      "side1": "spettacolo, lo",
      "side2": "show, play"
    },
    {
      "side1": "spinaci, gli",
      "side2": "spinach"
    },
    {
      "side1": "squadra, la",
      "side2": "team"
    },
    {
      "side1": "stadio, lo",
      "side2": "stadium"
    },
    {
      "side1": "stella, la (del cinema)",
      "side2": "film star"
    },
    {
      "side1": "strumento, lo (musicale)",
      "side2": "instrument"
    },
    {
      "side1": "succo di frutta, il",
      "side2": "fruit juice"
    },
    {
      "side1": "suggerire",
      "side2": "to suggest"
    },
    {
      "side1": "suonare",
      "side2": "to play an instrument, ring a bell"
    },
    {
      "side1": "tatuaggio, il",
      "side2": "tattoo"
    },
    {
      "side1": "telegiornale, il",
      "side2": "television news"
    },
    {
      "side1": "tempo libero, il",
      "side2": "free time"
    },
    {
      "side1": "tennis da tavolo, il",
      "side2": "table tennis"
    },
    {
      "side1": "toccare",
      "side2": "to touch"
    },
    {
      "side1": "tornare",
      "side2": "to return, turn"
    },
    {
      "side1": "torta, la",
      "side2": "cake"
    },
    {
      "side1": "uovo, l’ (le uova)",
      "side2": "egg, eggs"
    },
    {
      "side1": "uva, l’",
      "side2": "grapes"
    }
  ],
  "tags": ["Italian", "identity", "culture"]
}
