{
  "id": 52,
  "title": "Local, national, international and global areas of interest (part 14)",
  "cards": [
    {
      "side1": "tossicodipendente, il/la",
      "side2": "drug addict"
    },
    {
      "side1": "trafficante di droga, il/la",
      "side2": "drug trafficker"
    },
    {
      "side1": "trattoria, la",
      "side2": "restaurant"
    },
    {
      "side1": "ubriacarsi",
      "side2": "to get drunk"
    },
    {
      "side1": "ubriaco",
      "side2": "drunk"
    },
    {
      "side1": "vandalismo, il",
      "side2": "vandalism"
    },
    {
      "side1": "vegetariano",
      "side2": "vegetarian"
    },
    {
      "side1": "verdura, la",
      "side2": "vegetables"
    },
    {
      "side1": "vigile del fuoco, il",
      "side2": "firefighter"
    },
    {
      "side1": "vizio, il",
      "side2": "bad habit"
    },
    {
      "side1": "voce, la",
      "side2": "voice"
    },
    {
      "side1": "volontario, il",
      "side2": "volunteer"
    },
    {
      "side1": "vuotare",
      "side2": "to empty"
    },
    {
      "side1": "vuoto",
      "side2": "empty"
    },
    {
      "side1": "zuccherato",
      "side2": "sugary"
    },
    {
      "side1": "acqua del rubinetto, l’",
      "side2": "tap water"
    },
    {
      "side1": "ambiente, l’",
      "side2": "environment"
    },
    {
      "side1": "aumento, l’",
      "side2": "increase"
    },
    {
      "side1": "benzina (senza piombo), la",
      "side2": "(lead free) petrol"
    },
    {
      "side1": "bidone dei rifiuti, il",
      "side2": "rubbish bin"
    },
    {
      "side1": "biodegradabile",
      "side2": "biodegradable"
    },
    {
      "side1": "bombolette spray, le",
      "side2": "spray cans"
    },
    {
      "side1": "bottiglia, la",
      "side2": "bottle"
    },
    {
      "side1": "buco dell’ozono, il",
      "side2": "hole in ozone layer"
    },
    {
      "side1": "buttare",
      "side2": "to throw away"
    },
    {
      "side1": "carbone, il",
      "side2": "coal"
    },
    {
      "side1": "carta, la",
      "side2": "paper"
    },
    {
      "side1": "contenitore, il",
      "side2": "container"
    },
    {
      "side1": "disastro, il",
      "side2": "disaster"
    },
    {
      "side1": "distruggere",
      "side2": "to destroy"
    }
  ],
  "tags": [
    "Italian",
    "local",
    "national",
    "international",
    "global",
    "areas",
    "interest"
  ]
}
